pemap/__init__.py
pemap/block.py
pemap/highlevel.py
pemap/items.py
pemap/reference.py
pemap/util.py
pemap/value.py
pemap-0.1.1.dist-info/LICENSE
pemap-0.1.1.dist-info/METADATA
pemap-0.1.1.dist-info/WHEEL
pemap-0.1.1.dist-info/top_level.txt
pemap-0.1.1.dist-info/RECORD
